wis3d/__init__.py
wis3d/server.py
wis3d/version.py
wis3d/wis3d.py
wis3d/app/out/404.html
wis3d/app/out/favicon.ico
wis3d/app/out/index.html
wis3d/app/out/_next/static/bOFtEjc6ZE9C7ytnInzCB/_buildManifest.js
wis3d/app/out/_next/static/bOFtEjc6ZE9C7ytnInzCB/_ssgManifest.js
wis3d/app/out/_next/static/chunks/274.c7ff2a4ba51d2707ffa1.js
wis3d/app/out/_next/static/chunks/305.844819be5fc556aa69a2.js
wis3d/app/out/_next/static/chunks/347.94d3aa958cf08dfa7bcf.js
wis3d/app/out/_next/static/chunks/450.6ccc55e2377cdaf98384.js
wis3d/app/out/_next/static/chunks/526-6b20f33621e9222e52eb.js
wis3d/app/out/_next/static/chunks/63.fe6cb19b6afbd62b2393.js
wis3d/app/out/_next/static/chunks/687.ead11497fd2d7a381859.js
wis3d/app/out/_next/static/chunks/72.c304ee2dea029e0c5511.js
wis3d/app/out/_next/static/chunks/925.d9f684c37bbd12bcb8f6.js
wis3d/app/out/_next/static/chunks/commons.0bf1ee3170b7c98e5e7f.js
wis3d/app/out/_next/static/chunks/framework-c93ed74a065331c4bd75.js
wis3d/app/out/_next/static/chunks/main-655ad0ce567efa01caa9.js
wis3d/app/out/_next/static/chunks/polyfills-a54b4f32bdc1ef890ddd.js
wis3d/app/out/_next/static/chunks/webpack-b0fdd32947f01953889b.js
wis3d/app/out/_next/static/chunks/pages/_app-96414e29b0d6704ca16c.js
wis3d/app/out/_next/static/chunks/pages/_error-82a806cd39f8ab3dc3ac.js
wis3d/app/out/_next/static/chunks/pages/index-2e2974cb8dc433882950.js
wis3d/app/out/images/disc.png
wis3d-1.0.1.dist-info/METADATA
wis3d-1.0.1.dist-info/WHEEL
wis3d-1.0.1.dist-info/entry_points.txt
wis3d-1.0.1.dist-info/top_level.txt
wis3d-1.0.1.dist-info/RECORD
