Metadata-Version: 2.1
Name: wis3d
Version: 1.0.1
Summary: A web-based 3D visualization tool for 3D computer vision.
Home-page: UNKNOWN
Author: Jingmeng Zhang, Hongcheng Zhao, Zijing Huang, Jiaming Sun
License: Apache License 2.0
Project-URL: Homepage, https://wis3d.readthedocs.io/en/latest/
Project-URL: Online Demo, http://wis3d.idr.ai/
Project-URL: Source Code, https://github.com/zju3dv/wis3d.git
Platform: UNKNOWN
Classifier: Programming Language :: Python :: 3
Classifier: License :: OSI Approved :: MIT License
Classifier: Operating System :: OS Independent
Requires-Python: >=3.6
Requires-Dist: numpy
Requires-Dist: trimesh (>=3.9.0)
Requires-Dist: cherrypy
Requires-Dist: pillow
Requires-Dist: scipy
Requires-Dist: transforms3d
Requires-Dist: torch
